imgurpoi/__init__.py
imgurpoi/cli_upload.py
imgurpoi/imgurpoi.py
tests/__init__.py
imgurpoi-0.0.6.dist-info/LICENSE
imgurpoi-0.0.6.dist-info/METADATA
imgurpoi-0.0.6.dist-info/WHEEL
imgurpoi-0.0.6.dist-info/top_level.txt
imgurpoi-0.0.6.dist-info/RECORD
