Metadata-Version: 2.1
Name: imgurpoi
Version: 0.0.6
Summary: UNKNOWN
Home-page: https://github.com/_/imgurpoi
Author: Cswl Coldwind
Author-email: cswl1337@gmail.com
Maintainer: Cswl Coldwind
Maintainer-email: cswl1337@gmail.com
License: MIT/Apache-2.0
Platform: UNKNOWN
Classifier: Development Status :: 4 - Beta
Classifier: Intended Audience :: Developers
Classifier: License :: OSI Approved :: MIT License
Classifier: License :: OSI Approved :: Apache Software License
Classifier: Natural Language :: English
Classifier: Operating System :: OS Independent
Classifier: Programming Language :: Python :: 2.7
Classifier: Programming Language :: Python :: 3.5
Classifier: Programming Language :: Python :: 3.6
Classifier: Programming Language :: Python :: Implementation :: CPython
Classifier: Programming Language :: Python :: Implementation :: PyPy
Requires-Dist: click
Requires-Dist: requests
